<DOMSymbolItem xmlns:xsi="http://www.w3.org/2001/XMLSchema-instance" xmlns="http://ns.adobe.com/xfl/2008/" name="CartographerIcon" itemID="58db79f2-0000062f" linkageExportForAS="true" linkageIdentifier="CartographerIcon" lastModified="1529911718">
  <timeline>
    <DOMTimeline name="CartographerIcon">
      <layers>
        <DOMLayer name="Icon" color="#4FFF4F" current="true" isSelected="true" autoNamed="false" heightMultiplier="2">
          <frames>
            <DOMFrame index="0" name="inactive" labelType="name" keyMode="9728">
              <Actionscript>
                <script><![CDATA[stop();]]></script>
              </Actionscript>
              <elements>
                <DOMBitmapInstance libraryItemName="Icons/Icon.png"/>
              </elements>
            </DOMFrame>
          </frames>
        </DOMLayer>
      </layers>
    </DOMTimeline>
  </timeline>
</DOMSymbolItem>